prettyson/__init__.py
prettyson/__main__.py
prettyson/definitions.py
prettyson/format.py
tests/__init__.py
tests/test_cli.py
tests/test_formatter.py
prettyson-0.0.2.dist-info/LICENSE
prettyson-0.0.2.dist-info/METADATA
prettyson-0.0.2.dist-info/WHEEL
prettyson-0.0.2.dist-info/entry_points.txt
prettyson-0.0.2.dist-info/top_level.txt
prettyson-0.0.2.dist-info/RECORD
