Metadata-Version: 2.1
Name: prettyson
Version: 0.0.2
Summary: A Python-based JSON file formatter
Home-page: https://github.com/kokkonisd/prettyson
Author: Dimitri Kokkonis
Author-email: kokkonisd@gmail.com
License: UNKNOWN
Platform: UNKNOWN
Classifier: Programming Language :: Python :: 3
Requires-Python: >=3.6
License-File: LICENSE
